spectHR/__init__.py
spectHR/install_notebook.py
spectHR/sitecustomize.py
spectHR/Actions/__init__.py
spectHR/Actions/csActions.py
spectHR/Actions/csBreathing.py
spectHR/Actions/.ipynb_checkpoints/__init__-checkpoint.py
spectHR/Actions/.ipynb_checkpoints/csActions-checkpoint.py
spectHR/Actions/.ipynb_checkpoints/csBreathing-checkpoint.py
spectHR/Actions/__pycache__/__init__.cpython-312.pyc
spectHR/Actions/__pycache__/csActions.cpython-312.pyc
spectHR/Actions/__pycache__/csBreathing.cpython-312.pyc
spectHR/App/__init__.py
spectHR/App/spectHRApp.py
spectHR/App/.ipynb_checkpoints/spectHRApp-checkpoint.py
spectHR/App/__pycache__/__init__.cpython-312.pyc
spectHR/App/__pycache__/spectHRApp.cpython-312.pyc
spectHR/DataSet/SpectHRDataset.py
spectHR/DataSet/__init__.py
spectHR/DataSet/.ipynb_checkpoints/SpectHRDataset-checkpoint.py
spectHR/DataSet/__pycache__/SpectHRDataset.cpython-312.pyc
spectHR/DataSet/__pycache__/__init__.cpython-312.pyc
spectHR/Plots/Gantt.py
spectHR/Plots/Poincare.py
spectHR/Plots/Welch.py
spectHR/Plots/__init__.py
spectHR/Plots/prepPlot.py
spectHR/Plots/.ipynb_checkpoints/Poincare-checkpoint.py
spectHR/Plots/.ipynb_checkpoints/prepPlot-checkpoint.py
spectHR/Plots/__pycache__/Gantt.cpython-312.pyc
spectHR/Plots/__pycache__/Poincare.cpython-312.pyc
spectHR/Plots/__pycache__/Welch.cpython-312.pyc
spectHR/Plots/__pycache__/__init__.cpython-312.pyc
spectHR/Plots/__pycache__/prepPlot.cpython-312.pyc
spectHR/Tools/Explode.py
spectHR/Tools/Logger.py
spectHR/Tools/Params.py
spectHR/Tools/Webdav.py
spectHR/Tools/__init__.py
spectHR/Tools/.ipynb_checkpoints/Explode-checkpoint.py
spectHR/Tools/.ipynb_checkpoints/Params-checkpoint.py
spectHR/Tools/.ipynb_checkpoints/__init__-checkpoint.py
spectHR/Tools/__pycache__/Explode.cpython-312.pyc
spectHR/Tools/__pycache__/Logger.cpython-312.pyc
spectHR/Tools/__pycache__/Params.cpython-312.pyc
spectHR/Tools/__pycache__/Webdav.cpython-312.pyc
spectHR/Tools/__pycache__/__init__.cpython-312.pyc
specthr-0.1.11.dist-info/METADATA
specthr-0.1.11.dist-info/WHEEL
specthr-0.1.11.dist-info/entry_points.txt
specthr-0.1.11.dist-info/top_level.txt
specthr-0.1.11.dist-info/RECORD
