Metadata-Version: 2.4
Name: spectHR
Version: 0.1.11
Summary: HRApp: An Interactive Heart Rate Variability (HRV) Analysis Tool
Home-page: https://github.com/MarkSpan/spectHR
Author: Mark Span
Author-email: m.m.span@rug.nl
License: GPL-2.0-only
Project-URL: Homepage, https://github.com/MarkSpan/spectHR
Classifier: Intended Audience :: Science/Research
Classifier: Topic :: Scientific/Engineering :: Bio-Informatics
Classifier: Topic :: Scientific/Engineering :: Medical Science Apps.
Classifier: Topic :: Scientific/Engineering :: Visualization
Requires-Python: >=3.10
Requires-Dist: ipython
Requires-Dist: ipympl
Requires-Dist: ipyvuetify
Requires-Dist: ipywidgets
Requires-Dist: jupyter
Requires-Dist: jupyterlab>=4.0.0
Requires-Dist: matplotlib
Requires-Dist: mplcursors
Requires-Dist: numpy
Requires-Dist: pandas
Requires-Dist: pyxdf
Requires-Dist: scipy
Requires-Dist: seaborn
Requires-Dist: wheel
Requires-Dist: easywebdav
Dynamic: author
Dynamic: author-email
Dynamic: classifier
Dynamic: description
Dynamic: description-content-type
Dynamic: home-page
Dynamic: license
Dynamic: project-url
Dynamic: requires-dist
Dynamic: requires-python
Dynamic: summary
